itranvias_api/__init__.py
itranvias_api/__main__.py
itranvias_api/queryitr/__init__.py
itranvias_api/queryitr/info.py
itranvias_api/queryitr/known_servers.py
itranvias_api/queryitr/lines.py
itranvias_api/queryitr/models.py
itranvias_api/queryitr/queryitr_adapter.py
itranvias_api/queryitr/stops.py
itranvias_api-0.1.1.dist-info/licenses/LICENSE
itranvias_api-0.1.1.dist-info/METADATA
itranvias_api-0.1.1.dist-info/WHEEL
itranvias_api-0.1.1.dist-info/entry_points.txt
itranvias_api-0.1.1.dist-info/top_level.txt
itranvias_api-0.1.1.dist-info/RECORD
