Metadata-Version: 2.4
Name: itranvias_api
Version: 0.1.1
Summary: Python API wrapper for the city of A Coruña public transport
Author-email: Pedro Rey Anca <contact@peprolinbot.com>
License-Expression: GPL-3.0-or-later
Project-URL: homepage, https://github.com/peprolinbot/itranvias_api
Project-URL: documentation, https://peprolinbot.github.io/itranvias_api
Project-URL: repository, https://github.com/peprolinbot/itranvias_api
Keywords: bus,buses,transport,public transport,galicia,api
Classifier: Development Status :: 4 - Beta
Classifier: Programming Language :: Python :: 3
Classifier: Topic :: Software Development :: Libraries :: Python Modules
Requires-Python: >=3.9
License-File: LICENSE
Requires-Dist: requests>=2.32.3
Dynamic: license-file
